metarmonitor/__init__.py
metarmonitor/__main__.py
metarmonitor/metarmonitor.py
metarmonitor/metarmonitor_gui.py
metarmonitor/metarxml.py
metarmonitor/images/amber.gif
metarmonitor/images/arrowdown.gif
metarmonitor/images/arrowstraight.gif
metarmonitor/images/arrowup.gif
metarmonitor/images/black.gif
metarmonitor/images/blue.gif
metarmonitor/images/cross.gif
metarmonitor/images/green.gif
metarmonitor/images/grey.gif
metarmonitor/images/red.gif
metarmonitor/images/tick.gif
metarmonitor/images/white.gif
metarmonitor/images/yellow1.gif
metarmonitor/images/yellow2.gif
metarmonitor-0.9.2.dist-info/DESCRIPTION.rst
metarmonitor-0.9.2.dist-info/METADATA
metarmonitor-0.9.2.dist-info/RECORD
metarmonitor-0.9.2.dist-info/WHEEL
metarmonitor-0.9.2.dist-info/entry_points.txt
metarmonitor-0.9.2.dist-info/metadata.json
metarmonitor-0.9.2.dist-info/top_level.txt
