Metadata-Version: 2.0
Name: metarmonitor
Version: 0.9.2
Summary: Monitor METAR and TAF reports
Home-page: www.metpod.co.uk
Author: Mark Baker
Author-email: mark2182@mac.com
License: MIT
Platform: UNKNOWN
Requires-Dist: apscheduler
Requires-Dist: requests
Requires-Dist: twilio
